{
  "id": "chen_shui_bian",
  "name": "陈水扁",
  "image": "/leaders/roc_taiwan/csb.jpg",
  "alternateNames": "阿扁",
  "title": "中华民国总统、民主进步党主席",
  "shortTitle": "总统",
  "factionId": "dpp",
  "birthYear": 1950,
  "deathYear": null,
  "reignStart": 2000,
  "reignEnd": 2008,
  "ancestralHome": "台南县官田乡（今台南市官田区）",
  "ancestralHomeCoords": [
    120.3161,
    23.1944
  ],
  "birthplace": "台湾台南官田",
  "birthplaceCoords": [
    120.31,
    23.19
  ],
  "ethnicity": "汉族",
  "color": "#009c1a",
  "dynastyId": "roc_taiwan",
  "quote": {
    "text": "难道阿扁错了吗？",
    "source": "陈水扁"
  },
  "bio": "陈水扁（1950年10月12日—），生于台湾台南，律师、政治人物。曾任中华民国第10、11任总统，民主进步党主席。早年作为美丽岛事件的辩护律师步入政坛。2000年代表民进党当选总统，实现了台湾历史上首次和平的政党轮替，打破了国民党在台湾长达半个世纪的连续执政。但在其第二任期内，因其本人及家族亲信卷入多起重大贪腐弊案，引发了声势浩大的“红衫军”倒扁运动。卸任后随即被捕入狱，成为中华民国历史上首位因贪污遭判刑并入狱的卸任元首。",
  "timeline": [
    {
      "year": 1950,
      "event": "出生于台南县官田乡的贫困农家。"
    },
    {
      "year": 1980,
      "event": "担任美丽岛事件被告的辩护律师，开始参与党外运动。"
    },
    {
      "year": 1994,
      "event": "在台北市长选举中击败黄大洲与赵少康，成为首位民进党籍台北市长。"
    },
    {
      "year": 1998,
      "event": "竞选台北市长连任失败，败给国民党籍的马英九。"
    },
    {
      "year": 2000,
      "event": "在总统大选中以微弱优势击败宋楚瑜和连战，当选第10任总统，实现首次政党轮替。"
    },
    {
      "year": 2004,
      "event": "在投票前一日发生“319枪击案”，最终以不到3万票的极微弱优势惊险连任。"
    },
    {
      "year": 2006,
      "event": "因家族及亲信贪腐丑闻爆发，台湾爆发百万人参与的“红衫军”倒扁运动。"
    },
    {
      "year": 2008,
      "event": "总统任期届满卸任。同年因涉嫌国务机要费案、洗钱等重罪被特侦组声押获准。"
    },
    {
      "year": 2010,
      "event": "因多起贪污案被判处有期徒刑20年，入监服刑。"
    },
    {
      "year": 2015,
      "event": "因健康问题（失智症及帕金森氏症等）获准保外就医，此后一直处于保外就医状态。"
    }
  ],
  "achievements": [
    {
      "title": "首次政党轮替",
      "description": "2000年的胜选打破了中国国民党在台湾长达55年的执政，完成了中华民国历史上第一次和平的政权交接，是台湾民主化进程中的重要里程碑。"
    },
    {
      "title": "军队国家化落实",
      "description": "在任内大力推动军队国家化，切断了国军与国民党的历史历史连结，确立了军队对民选政府及国家效忠的宪政原则。"
    }
  ],
  "controversies": [
    {
      "title": "重大贪腐丑闻",
      "description": "任内及卸任后，其本人、妻子吴淑珍及众多亲信被查出涉入“国务机要费案”、“龙潭购地弊案”及海外洗钱等大规模贪腐案件，使其政治声誉彻底扫地。"
    },
    {
      "title": "319枪击案争议",
      "description": "2004年总统大选投票前夕的枪击案极大影响了选情，因案情扑朔迷离、凶手溺毙，长期被泛蓝阵营质疑为自导自演的政治操作。"
    },
    {
      "title": "烽火外交与激化两岸",
      "description": "为转移国内施政不力及贪腐焦点，后期大力推动“一边一国”、“入联公投”等激进台独路线，不仅导致台海局势高度紧张，也被当时的美国小布什政府严厉批评为“麻烦制造者”。"
    }
  ],
  "ratings": {
    "economy": 55,
    "military": 65,
    "culture": 70,
    "ideology": 78,
    "practice": 52,
    "diplomacy": 40,
    "legacy": 50,
    "benevolence": 60,
    "stability": 58,
    "capability": 68
  },
  "ratingsExplain": {
    "military": "推动防务自主与军购议题，但受预算与两岸结构限制明显。",
    "benevolence": "社会福利与本土权益议程有所推进，政治对立又削弱整体社会感受。",
    "economy": "执政期经济表现受外部周期与内部纷争影响，结构性改革力度有限。",
    "culture": "强化台湾主体教育与文化叙事，提升本土认同但也加剧分歧。",
    "ideology": "民进党式民主与主体性论述清晰，意识形态辨识度很高。",
    "practice": "朝小野大下施政受阻，加之贪腐案冲击，实践成绩明显受损。",
    "diplomacy": "国际空间拓展有限，对外关系长期受“一中框架”压缩。",
    "legacy": "实现政党轮替具里程碑意义，但个人争议削弱了历史净评价。",
    "stability": "蓝绿对抗在其任内显著升温，社会情绪波动较大。",
    "capability": "选举动员和政治攻防能力强于长期治理整合能力。"
  },
  "summary": "陈水扁是台湾民主化历程中极具象征意义却又令人唏嘘的政治人物。他出身三级贫户，凭借出色的选举才华与党外运动的资历，成功终结了国民党的半世纪威权统治，标志着台湾民主的初步成熟。然而，他主政后期深陷极其严重的家族贪腐丑闻，以及为操弄选举而采取的撕裂族群、激化两岸对抗的极端操作，使其最终从“台湾之子”沦为阶下囚，对台湾社会的政治信任造成了深远的伤害。"
}